ooengine/__init__.py
ooengine/__main__.py
ooengine/commands.py
ooengine/main.py
ooengine/test_inputs.py
ooengine/usernamelib.py
ooengine-0.2.1.dist-info/LICENSE
ooengine-0.2.1.dist-info/METADATA
ooengine-0.2.1.dist-info/WHEEL
ooengine-0.2.1.dist-info/top_level.txt
ooengine-0.2.1.dist-info/RECORD
