Metadata-Version: 2.1
Name: ooengine
Version: 0.2.1
Summary: A object-oriented MUD engine
Author-email: Themadpunter <themadpunter@noreply.com>
Project-URL: Homepage, https://github.com/familycomicsstudios/ooengine
Project-URL: Bug Tracker, https://github.com/familycomicsstudios/ooengine/issues
Classifier: Programming Language :: Python :: 3
Classifier: Operating System :: OS Independent
Classifier: License :: OSI Approved :: GNU General Public License v3 (GPLv3)
Requires-Python: >=3.10
License-File: LICENSE
